license
weaklru/__init__.py
weaklru-0.1.1.dist-info/license
weaklru-0.1.1.dist-info/WHEEL
weaklru-0.1.1.dist-info/METADATA
weaklru-0.1.1.dist-info/RECORD
