Metadata-Version: 2.1
Name: weaklru
Version: 0.1.1
Summary: Combination of weakref cache and LRU cache.
Home-page: https://github.com/AtakamaLLC/weaklru
License: MIT
Author: Erik Aronesty
Author-email: erik@q32.com
Classifier: License :: OSI Approved :: MIT License
Classifier: Programming Language :: Python :: 2
Classifier: Programming Language :: Python :: 2.7
Classifier: Programming Language :: Python :: 3
Classifier: Programming Language :: Python :: 3.4
Classifier: Programming Language :: Python :: 3.5
Classifier: Programming Language :: Python :: 3.6
Classifier: Programming Language :: Python :: 3.7
Classifier: Programming Language :: Python :: 3.8
Project-URL: Repository, https://github.com/AtakamaLLC/weaklru
